datatable/__init__.py
datatable/columns.py
datatable/tables.py
etl/__init__.py
etl/etl_spark.py
etlbr-1.0.0.0.dist-info/METADATA
etlbr-1.0.0.0.dist-info/WHEEL
etlbr-1.0.0.0.dist-info/top_level.txt
etlbr-1.0.0.0.dist-info/RECORD
