Metadata-Version: 2.1
Name: etlbr
Version: 1.0.0.0
Summary: Lib etl
Home-page: https://github.com/jonathan-works/etlbr
Author: Jonathan
Author-email: jonathan-works@hotmail.com
Classifier: Programming Language :: Python :: 3
Classifier: License :: OSI Approved :: MIT License
Classifier: Operating System :: OS Independent
Requires-Python: >=3.6
